dbETL/__init__.py
dbETL/batch2mysql.py
dbETL/pyAPI.py
dbETL-0.0.8.dist-info/DESCRIPTION.rst
dbETL-0.0.8.dist-info/METADATA
dbETL-0.0.8.dist-info/RECORD
dbETL-0.0.8.dist-info/WHEEL
dbETL-0.0.8.dist-info/entry_points.txt
dbETL-0.0.8.dist-info/metadata.json
dbETL-0.0.8.dist-info/top_level.txt
