Metadata-Version: 2.0
Name: dbETL
Version: 0.0.8
Summary: database batch ETL helper
Home-page: https://github.com/shichaoji/dbETL
Author: Shichao(Richard) Ji
Author-email: jshichao@vt.edu
License: MIT
Download-URL: https://github.com/shichaoji/dbETL/archive/0.1.tar.gz
Keywords: database,ETL,mysql,scrapyhub
Platform: UNKNOWN
Classifier: License :: OSI Approved :: MIT License
Classifier: Programming Language :: Python :: 2
Requires-Dist: pymysql
